jupyter_ux/__init__.py
jupyter_ux/_version.py
jupyter_ux/handlers.py
jupyter_ux/tests/__init__.py
jupyter_ux/tests/test_handlers.py
jupyter_ux-0.0.3.data/data/etc/jupyter/jupyter_notebook_config.d/jupyter_ux.json
jupyter_ux-0.0.3.data/data/etc/jupyter/jupyter_server_config.d/jupyter_ux.json
jupyter_ux-0.0.3.data/data/share/jupyter/labextensions/@datalayer/jupyter-ux/build_log.json
jupyter_ux-0.0.3.data/data/share/jupyter/labextensions/@datalayer/jupyter-ux/package.json
jupyter_ux-0.0.3.data/data/share/jupyter/labextensions/@datalayer/jupyter-ux/schemas/@datalayer/jupyter-ui/package.json.orig
jupyter_ux-0.0.3.data/data/share/jupyter/labextensions/@datalayer/jupyter-ux/schemas/@datalayer/jupyter-ui/plugin.json
jupyter_ux-0.0.3.data/data/share/jupyter/labextensions/@datalayer/jupyter-ux/static/lib_index_js.2b53d51b180185a7229d.js
jupyter_ux-0.0.3.data/data/share/jupyter/labextensions/@datalayer/jupyter-ux/static/lib_index_js.2b53d51b180185a7229d.js.map
jupyter_ux-0.0.3.data/data/share/jupyter/labextensions/@datalayer/jupyter-ux/static/node_modules_object-assign_index_js.3207811d53dfa7ed4b8b.js
jupyter_ux-0.0.3.data/data/share/jupyter/labextensions/@datalayer/jupyter-ux/static/node_modules_object-assign_index_js.3207811d53dfa7ed4b8b.js.map
jupyter_ux-0.0.3.data/data/share/jupyter/labextensions/@datalayer/jupyter-ux/static/remoteEntry.8272756ade95519eb51e.js
jupyter_ux-0.0.3.data/data/share/jupyter/labextensions/@datalayer/jupyter-ux/static/remoteEntry.8272756ade95519eb51e.js.map
jupyter_ux-0.0.3.data/data/share/jupyter/labextensions/@datalayer/jupyter-ux/static/style.js
jupyter_ux-0.0.3.data/data/share/jupyter/labextensions/@datalayer/jupyter-ux/static/style_index_js.7c833861237095e42890.js
jupyter_ux-0.0.3.data/data/share/jupyter/labextensions/@datalayer/jupyter-ux/static/style_index_js.7c833861237095e42890.js.map
jupyter_ux-0.0.3.dist-info/METADATA
jupyter_ux-0.0.3.dist-info/WHEEL
jupyter_ux-0.0.3.dist-info/licenses/LICENSE
jupyter_ux-0.0.3.dist-info/RECORD
